entitykb/__init__.py
entitykb/__version__.py
entitykb/base.py
entitykb/cache.py
entitykb/config.py
entitykb/crypto.py
entitykb/env.py
entitykb/exceptions.py
entitykb/interfaces.py
entitykb/logging.py
entitykb/reflection.py
entitykb/cli/__init__.py
entitykb/cli/__main__.py
entitykb/cli/cli.py
entitykb/cli/commands.py
entitykb/cli/patterns.py
entitykb/cli/readers.py
entitykb/cli/services.py
entitykb/cli/users.py
entitykb/cli/writers.py
entitykb/contrib/__init__.py
entitykb/contrib/date/__init__.py
entitykb/contrib/date/grammar.lark
entitykb/contrib/date/model.py
entitykb/contrib/date/resolvers.py
entitykb/contrib/email/__init__.py
entitykb/contrib/email/model.py
entitykb/contrib/email/resolvers.py
entitykb/deps/__init__.py
entitykb/deps/eff-long.txt.gz
entitykb/deps/environ.py
entitykb/deps/formatters.py
entitykb/graph/__init__.py
entitykb/graph/edges.py
entitykb/graph/graph.py
entitykb/graph/nodes.py
entitykb/graph/patterns.py
entitykb/http/__init__.py
entitykb/http/app.py
entitykb/http/dev.py
entitykb/http/prod.py
entitykb/http/routes.py
entitykb/http/admin/package-lock.json
entitykb/http/admin/package.json
entitykb/http/admin/rollup.config.js
entitykb/http/admin/public/global.css
entitykb/http/admin/public/index.html
entitykb/http/admin/public/app/bundle.css
entitykb/http/admin/public/app/bundle.css.map
entitykb/http/admin/public/app/bundle.js
entitykb/http/admin/public/app/bundle.js.map
entitykb/http/admin/public/images/favicon.png
entitykb/http/admin/public/images/logo.png
entitykb/http/admin/public/libs/jquery/jquery.min.js
entitykb/http/admin/public/libs/jsonview/jsonview.min.css
entitykb/http/admin/public/libs/jsonview/jsonview.min.js
entitykb/http/admin/public/libs/semantic-ui/semantic.min.css
entitykb/http/admin/public/libs/semantic-ui/semantic.min.js
entitykb/http/admin/public/libs/semantic-ui/components/icon.min.css
entitykb/http/admin/public/libs/themes/default/assets/fonts/brand-icons.eot
entitykb-21.7.28.dist-info/LICENSE
entitykb-21.7.28.dist-info/METADATA
entitykb-21.7.28.dist-info/WHEEL
entitykb-21.7.28.dist-info/entry_points.txt
entitykb-21.7.28.dist-info/top_level.txt
entitykb-21.7.28.dist-info/RECORD
