Metadata-Version: 2.1
Name: entitykb
Version: 21.7.28
Summary: Python toolkit for rapidly developing knowledge bases
Home-page: https://github.com/genomoncology/entitykb
Author: Ian Maurer
Author-email: ian@genomoncology.com
License: UNKNOWN
Platform: UNKNOWN
Classifier: License :: OSI Approved :: MIT License
Classifier: Development Status :: 4 - Beta
Classifier: Intended Audience :: Developers
Classifier: Natural Language :: English
Classifier: Operating System :: POSIX :: Linux
Classifier: Operating System :: MacOS :: MacOS X
Classifier: Operating System :: Microsoft :: Windows
Classifier: Programming Language :: Python :: 3
Classifier: Programming Language :: Python :: 3.6
Classifier: Programming Language :: Python :: 3.7
Classifier: Programming Language :: Python :: 3.8
Classifier: Programming Language :: Python :: 3.9
Classifier: Topic :: Scientific/Engineering
Requires-Python: >=3.6
Requires-Dist: aiofiles (>=0.6.0)
Requires-Dist: DAWG (>=0.8.0)
Requires-Dist: Pyro5 (>=5.12)
Requires-Dist: diskcache (>=5.1.0)
Requires-Dist: fastapi (>=0.61.2)
Requires-Dist: lark-parser (>=0.8.9)
Requires-Dist: msgpack (>=1.0.2)
Requires-Dist: passlib[bcrypt] (>=1.7.0)
Requires-Dist: pyjwt (==1.7.1)
Requires-Dist: python-multipart (==0.0.5)
Requires-Dist: smart-open (>=3.0.0)
Requires-Dist: tabulate (>=0.8.0)
Requires-Dist: translitcodec (>=0.5.2)
Requires-Dist: typer (>=0.3.2)
Requires-Dist: ujson (>=4.0.1)
Requires-Dist: uvicorn (>=0.12.2)
